{
  "blogs": [
    {
      "id": "33b5"
    },
    {
      "id": "dfa5",
      "title": "dfeu",
      "author": "efnej",
      "body": "ekfn"
    },
    {
      "id": "f0ac",
      "title": "dfeu",
      "author": "efnej",
      "body": "ekfn"
    },
    {
      "id": "41ab",
      "title": "eevffvd",
      "author": "jnfncjrj",
      "body": "fn cjrvnjrv"
    },
    {
      "id": "6322",
      "title": "Kings",
      "author": "King Mbuda",
      "body": "due2cbvye2vch3civucixevucvxu"
    },
    {
      "id": "9c50",
      "title": "king",
      "author": "King Mbuda",
      "body": "ejcbeuvb"
    },
    {
      "id": "22a1",
      "title": "Kings",
      "author": "King Mbuda",
      "body": "Lord"
    },
    {
      "id": "c717",
      "title": "",
      "author": "",
      "body": ""
    },
    {
      "id": "1ef7",
      "title": "",
      "author": "",
      "body": ""
    },
    {
      "id": "f2d8",
      "title": "Joony",
      "author": "Prince",
      "body": "The Lord God Almight"
    },
    {
      "id": "58d8",
      "title": "",
      "author": "",
      "body": ""
    },
    {
      "id": "4a1f",
      "title": "",
      "author": "",
      "body": ""
    },
    {
      "id": "12da",
      "title": "Kingdom Principles",
      "author": "Mbuda Branice Njira",
      "body": "Kingdom principles are foundational truths that guide how a person should live in alignment with God’s kingdom, reflecting His character and purposes on Earth. These principles often emphasize love, justice, peace, and faithfulness. Below are some key kingdom principles that can be applied to life:\n\n### 1. **Love and Compassion**  \n   - **Principle**: Love is the greatest commandment (Matthew 22:37-40). \n   - **Application**: Prioritize love for God and others in all actions, showing compassion even to those who may not deserve it.\n\n### 2. **Humility and Servanthood**  \n   - **Principle**: The greatest among you will be your servant (Matthew 23:11-12). \n   - **Application**: Pursue a humble attitude, putting the needs of others before your own and seeking to serve rather than be served.\n\n### 3. **Faithfulness and Stewardship**  \n   - **Principle**: Be faithful in little, and you will be trusted with more (Luke 16:10).  \n   - **Application**: Be diligent and responsible with what God has entrusted to you—whether that be talents, resources, or time.\n\n### 4. **Forgiveness and Reconciliation**  \n   - **Principle**: Forgive others as Christ has forgiven you (Ephesians 4:32).  \n   - **Application**: Cultivate a heart of forgiveness, resolving conflicts and reconciling with others, understanding that we are forgiven by God daily.\n\n### 5. **Seek First God’s Kingdom**  \n   - **Principle**: Seek first the kingdom of God and His righteousness (Matthew 6:33).  \n   - **Application**: Focus on pursuing God's will and righteousness above all else. Trust that when you do, your needs will be met.\n\n### 6. **Peace and Reconciliation**  \n   - **Principle**: Blessed are the peacemakers (Matthew 5:9).  \n   - **Application**: Actively pursue peace in your relationships and communities. Strive to be a mediator, fostering harmony and understanding.\n\n### 7. **Generosity and Giving**  \n   - **Principle**: It is more blessed to give than to receive (Acts 20:35).  \n   - **Application**: Live generously with your time, talents, and finances, recognizing that God’s blessings are meant to be shared.\n\n### 8. **Truth and Integrity**  \n   - **Principle**: Let your yes be yes, and your no be no (Matthew 5:37).  \n   - **Application**: Live a life of honesty and integrity, holding fast to the truth and being a person whose word is trustworthy.\n\n### 9. **Prayer and Dependence on God**  \n   - **Principle**: Ask, and it will be given to you; seek, and you will find (Matthew 7:7).  \n   - **Application**: Cultivate a lifestyle of prayer, acknowledging your dependence on God for guidance, provision, and strength.\n\n### 10. **Kingdom Purpose and Mission**  \n   - **Principle**: Go and make disciples of all nations (Matthew 28:19-20).  \n   - **Application**: Recognize that you have a kingdom purpose to share the love of Christ with others, and actively engage in the mission of spreading the Gospel.\n\n### 11. **Joy and Gratitude**  \n   - **Principle**: Rejoice in the Lord always (Philippians 4:4).  \n   - **Application**: Cultivate an attitude of joy and gratitude, regardless of circumstances, knowing that God is always with you and working for your good.\n\n### 12. **Righteousness and Justice**  \n   - **Principle**: Let justice roll down like waters, and righteousness like an ever-flowing stream (Amos 5:24).  \n   - **Application**: Stand up for justice, fight against oppression, and advocate for fairness and righteousness in society.\n\nThese kingdom principles are meant to transform how we think, act, and interact with others, reflecting God’s will and His reign in our lives. How do you see these principles playing out in your own life?"
    }
  ]
}